<annotation>
	<folder>train</folder>
	<filename>IMG_0522.jpg</filename>
	<path>/Users/kaiqianzhu/Desktop/images/train/IMG_0522.jpg</path>
	<source>
		<database>Unknown</database>
	</source>
	<size>
		<width>806</width>
		<height>605</height>
		<depth>3</depth>
	</size>
	<segmented>0</segmented>
	<object>
		<name>nanoleaf</name>
		<pose>Unspecified</pose>
		<truncated>0</truncated>
		<difficult>0</difficult>
		<bndbox>
			<xmin>5</xmin>
			<ymin>3</ymin>
			<xmax>690</xmax>
			<ymax>545</ymax>
		</bndbox>
	</object>
</annotation>
